tree_sitter_ghactions/__init__.py
tree_sitter_ghactions/__init__.pyi
tree_sitter_ghactions/_binding.abi3.so
tree_sitter_ghactions/binding.c
tree_sitter_ghactions/py.typed
tree_sitter_ghactions/queries/highlights.scm
tree_sitter_ghactions/queries/injections.scm
tree_sitter_ghactions-0.2.5.dist-info/METADATA
tree_sitter_ghactions-0.2.5.dist-info/WHEEL
tree_sitter_ghactions-0.2.5.dist-info/top_level.txt
tree_sitter_ghactions-0.2.5.dist-info/RECORD
tree_sitter_ghactions-0.2.5.dist-info/licenses/LICENSE
